lymphoseq/__init__.py
lymphoseq/analysis/__init__.py
lymphoseq/analysis/alignment.py
lymphoseq/analysis/comparative.py
lymphoseq/analysis/diversity.py
lymphoseq/analysis/genes.py
lymphoseq/analysis/statistics.py
lymphoseq/cli/__init__.py
lymphoseq/cli/main.py
lymphoseq/database/__init__.py
lymphoseq/database/search.py
lymphoseq/parsers/__init__.py
lymphoseq/parsers/airr_schema.py
lymphoseq/parsers/base_parser.py
lymphoseq/parsers/immunoseq_parser.py
lymphoseq/parsers/mixcr_parser.py
lymphoseq/parsers/tenx_parser.py
lymphoseq/parsers/utils.py
lymphoseq/parsers/utils_enhanced.py
lymphoseq/sequence/__init__.py
lymphoseq/sequence/chain_merge.py
lymphoseq/sequence/filtering.py
lymphoseq/visualization/__init__.py
lymphoseq/visualization/plots.py
lymphoseq-0.1.0.dist-info/licenses/LICENSE
lymphoseq-0.1.0.dist-info/METADATA
lymphoseq-0.1.0.dist-info/WHEEL
lymphoseq-0.1.0.dist-info/entry_points.txt
lymphoseq-0.1.0.dist-info/top_level.txt
lymphoseq-0.1.0.dist-info/RECORD
