Metadata-Version: 2.4
Name: lymphoseq
Version: 0.1.0
Summary: Python toolkit for analyzing high-throughput T and B cell receptor sequencing data
Author-email: Shashidhar Ravishankar <sravisha@fredhutch.org>
License: MIT
Project-URL: Homepage, https://github.com/shashidhar22/lymphoseq
Project-URL: Documentation, https://lymphoseq.readthedocs.io
Project-URL: Repository, https://github.com/shashidhar22/lymphoseq
Project-URL: Bug Tracker, https://github.com/shashidhar22/lymphoseq/issues
Keywords: immunology,tcr,bcr,airr,bioinformatics
Classifier: Development Status :: 3 - Alpha
Classifier: Intended Audience :: Science/Research
Classifier: License :: OSI Approved :: MIT License
Classifier: Programming Language :: Python :: 3
Classifier: Programming Language :: Python :: 3.8
Classifier: Programming Language :: Python :: 3.9
Classifier: Programming Language :: Python :: 3.10
Classifier: Programming Language :: Python :: 3.11
Classifier: Topic :: Scientific/Engineering :: Bio-Informatics
Requires-Python: >=3.8
License-File: LICENSE
Requires-Dist: pandas>=1.5.0
Requires-Dist: numpy>=1.21.0
Requires-Dist: polars>=0.19.0
Requires-Dist: pyarrow>=10.0.0
Requires-Dist: dask[dataframe]>=2023.1.0
Requires-Dist: pydantic>=2.0.0
Requires-Dist: typer>=0.9.0
Requires-Dist: rich>=13.0.0
Requires-Dist: plotly>=5.15.0
Requires-Dist: seaborn>=0.12.0
Requires-Dist: matplotlib>=3.6.0
Requires-Dist: scipy>=1.9.0
Requires-Dist: scikit-learn>=1.1.0
Requires-Dist: biopython>=1.80
Requires-Dist: networkx>=2.8
Requires-Dist: pyyaml>=6.0
Provides-Extra: dev
Requires-Dist: pytest>=7.0; extra == "dev"
Requires-Dist: pytest-cov>=4.0; extra == "dev"
Requires-Dist: black>=23.0; extra == "dev"
Requires-Dist: isort>=5.12; extra == "dev"
Requires-Dist: mypy>=1.0; extra == "dev"
Requires-Dist: ruff>=0.1.0; extra == "dev"
Requires-Dist: pre-commit>=3.0; extra == "dev"
Provides-Extra: docs
Requires-Dist: sphinx>=6.0; extra == "docs"
Requires-Dist: sphinx-rtd-theme>=1.3; extra == "docs"
Requires-Dist: myst-parser>=2.0; extra == "docs"
Requires-Dist: nbsphinx>=0.9; extra == "docs"
Provides-Extra: benchmark
Requires-Dist: pytest-benchmark>=4.0; extra == "benchmark"
Requires-Dist: memory-profiler>=0.61; extra == "benchmark"
Dynamic: license-file
